felonfinder/FelonFinder.py
felonfinder/__init__.py
felonfinder/cfg/config.ini
felonfinder/img/mode.png
felonfinder/img/unknown.png
felonfinder/img/faces/000007.jpg
felonfinder/img/faces/000008.jpg
felonfinder/img/faces/000009.jpg
felonfinder/img/faces/000010.jpg
felonfinder/img/faces/000011.jpg
felonfinder/img/faces/000012.jpg
felonfinder/img/faces/000013.jpg
felonfinder/img/faces/000014.jpg
felonfinder/img/faces/000015.jpg
felonfinder/img/faces/000016.jpg
felonfinder/img/faces/000017.jpg
felonfinder/img/faces/000018.jpg
felonfinder/img/faces/000019.jpg
felonfinder/img/faces/000020.jpg
felonfinder/img/faces/000021.jpg
felonfinder/img/faces/000022.jpg
felonfinder/img/faces/000023.jpg
felonfinder/img/faces/000024.jpg
felonfinder/img/faces/000025.jpg
felonfinder/img/faces/000026.jpg
felonfinder/img/faces/000027.jpg
felonfinder/img/faces/000028.jpg
felonfinder/img/faces/000029.jpg
felonfinder/img/faces/000030.jpg
felonfinder/img/faces/000031.jpg
felonfinder/img/faces/000032.jpg
felonfinder/img/faces/000033.jpg
felonfinder/img/faces/000034.jpg
felonfinder/img/faces/000035.jpg
felonfinder/img/faces/000036.jpg
felonfinder/img/faces/000037.jpg
felonfinder/img/faces/000038.jpg
felonfinder/img/faces/000039.jpg
felonfinder/img/faces/000040.jpg
felonfinder/img/faces/000041.jpg
felonfinder/img/faces/000042.jpg
felonfinder/img/faces/000043.jpg
felonfinder/img/faces/000044.jpg
felonfinder/img/faces/000045.jpg
felonfinder/img/faces/000046.jpg
felonfinder/img/faces/000047.jpg
felonfinder/img/faces/000048.jpg
felonfinder/img/faces/000049.jpg
felonfinder/img/faces/000050.jpg
felonfinder/img/faces/000051.jpg
felonfinder/img/faces/000052.jpg
felonfinder/img/faces/000053.jpg
felonfinder/img/faces/000054.jpg
felonfinder/img/faces/000055.jpg
felonfinder/img/faces/000056.jpg
felonfinder/img/faces/000057.jpg
felonfinder/img/faces/000058.jpg
felonfinder/img/faces/000059.jpg
felonfinder/img/faces/000060.jpg
felonfinder/img/faces/000061.jpg
felonfinder/img/faces/000062.jpg
felonfinder-1.0.3.dist-info/LICENSE.txt
felonfinder-1.0.3.dist-info/METADATA
felonfinder-1.0.3.dist-info/WHEEL
felonfinder-1.0.3.dist-info/entry_points.txt
felonfinder-1.0.3.dist-info/top_level.txt
felonfinder-1.0.3.dist-info/RECORD
